{
    "name": "SoftwareApplication",
    "prop": [
        {
            "name": "downloadUrl",
            "desc": "If the file can be downloaded, URL to download the binary.",
            "type": [
                "URL"
            ]
        },
        {
            "name": "softwareRequirements",
            "desc": "Component dependency requirements for application. This includes runtime environments and shared libraries that are not included in the application distribution package, but required to run the application (Examples: DirectX, Java or .NET runtime).",
            "type": [
                "Text",
                "URL"
            ]
        },
        {
            "name": "permissions",
            "desc": "Permission(s) required to run the app (for example, a mobile app may require full internet access or may run only on wifi).",
            "type": [
                "Text"
            ]
        },
        {
            "name": "processorRequirements",
            "desc": "Processor architecture required to run the application (e.g. IA64).",
            "type": [
                "Text"
            ]
        },
        {
            "name": "availableOnDevice",
            "desc": "Device required to run the application. Used in cases where a specific make/model is required to run the application.",
            "type": [
                "Text"
            ]
        },
        {
            "name": "featureList",
            "desc": "Features or modules provided by this application (and possibly required by other applications).",
            "type": [
                "Text",
                "URL"
            ]
        },
        {
            "name": "applicationSubCategory",
            "desc": "Subcategory of the application, e.g. 'Arcade Game'.",
            "type": [
                "Text",
                "URL"
            ]
        },
        {
            "name": "device",
            "desc": "Device required to run the application. Used in cases where a specific make/model is required to run the application.",
            "type": [
                "Text"
            ]
        },
        {
            "name": "applicationCategory",
            "desc": "Type of software application, e.g. 'Game, Multimedia'.",
            "type": [
                "Text",
                "URL"
            ]
        },
        {
            "name": "softwareVersion",
            "desc": "Version of the software instance.",
            "type": [
                "Text"
            ]
        },
        {
            "name": "storageRequirements",
            "desc": "Storage requirements (free space required).",
            "type": [
                "URL",
                "Text"
            ]
        },
        {
            "name": "applicationSuite",
            "desc": "The name of the application suite to which the application belongs (e.g. Excel belongs to Office).",
            "type": [
                "Text"
            ]
        },
        {
            "name": "memoryRequirements",
            "desc": "Minimum memory requirements.",
            "type": [
                "Text",
                "URL"
            ]
        },
        {
            "name": "screenshot",
            "desc": "A link to a screenshot image of the app.",
            "type": [
                "URL",
                "ImageObject"
            ]
        },
        {
            "name": "countriesSupported",
            "desc": "Countries for which the application is supported. You can also provide the two-letter ISO 3166-1 alpha-2 country code.",
            "type": [
                "Text"
            ]
        },
        {
            "name": "softwareHelp",
            "desc": "Software application help.",
            "type": [
                "CreativeWork"
            ]
        },
        {
            "name": "softwareAddOn",
            "desc": "Additional content for a software application.",
            "type": [
                "SoftwareApplication"
            ]
        },
        {
            "name": "releaseNotes",
            "desc": "Description of what changed in this version.",
            "type": [
                "URL",
                "Text"
            ]
        },
        {
            "name": "supportingData",
            "desc": "Supporting data for a SoftwareApplication.",
            "type": [
                "DataFeed"
            ]
        },
        {
            "name": "requirements",
            "desc": "Component dependency requirements for application. This includes runtime environments and shared libraries that are not included in the application distribution package, but required to run the application (Examples: DirectX, Java or .NET runtime).",
            "type": [
                "Text",
                "URL"
            ]
        },
        {
            "name": "countriesNotSupported",
            "desc": "Countries for which the application is not supported. You can also provide the two-letter ISO 3166-1 alpha-2 country code.",
            "type": [
                "Text"
            ]
        },
        {
            "name": "operatingSystem",
            "desc": "Operating systems supported (Windows 7, OSX 10.6, Android 1.6).",
            "type": [
                "Text"
            ]
        },
        {
            "name": "fileSize",
            "desc": "Size of the application / package (e.g. 18MB). In the absence of a unit (MB, KB etc.), KB will be assumed.",
            "type": [
                "Text"
            ]
        },
        {
            "name": "installUrl",
            "desc": "URL at which the app may be installed, if different from the URL of the item.",
            "type": [
                "URL"
            ]
        }
    ],
    "from": {
        "CreativeWork": [
            {
                "name": "about",
                "desc": "The subject matter of the content.",
                "type": [
                    "Thing"
                ]
            },
            {
                "name": "educationalAlignment",
                "desc": "An alignment to an established educational framework.",
                "type": [
                    "AlignmentObject"
                ]
            },
            {
                "name": "associatedMedia",
                "desc": "A media object that encodes this CreativeWork. This property is a synonym for encoding.",
                "type": [
                    "MediaObject"
                ]
            },
            {
                "name": "funder",
                "desc": "A person or organization that supports (sponsors) something through some kind of financial contribution.",
                "type": [
                    "Person",
                    "Organization"
                ]
            },
            {
                "name": "position",
                "desc": "The position of an item in a series or sequence of items.",
                "type": [
                    "Integer",
                    "Text"
                ]
            },
            {
                "name": "audio",
                "desc": "An embedded audio object.",
                "type": [
                    "AudioObject"
                ]
            },
            {
                "name": "workExample",
                "desc": "Example/instance/realization/derivation of the concept of this creative work. eg. The paperback edition, first edition, or eBook.",
                "type": [
                    "CreativeWork"
                ]
            },
            {
                "name": "provider",
                "desc": "The service provider, service operator, or service performer; the goods producer. Another party (a seller) may offer those services or goods on behalf of the provider. A provider may also serve as the seller.",
                "type": [
                    "Organization",
                    "Person"
                ]
            },
            {
                "name": "encoding",
                "desc": "A media object that encodes this CreativeWork. This property is a synonym for associatedMedia.",
                "type": [
                    "MediaObject"
                ]
            },
            {
                "name": "interactivityType",
                "desc": "The predominant mode of learning supported by the learning resource. Acceptable values are 'active', 'expositive', or 'mixed'.",
                "type": [
                    "Text"
                ]
            },
            {
                "name": "accessibilitySummary",
                "desc": "A human-readable summary of specific accessibility features or deficiencies, consistent with the other accessibility metadata but expressing subtleties such as \"short descriptions are present but long descriptions will be needed for non-visual users\" or \"short descriptions are present and no long descriptions are needed.\"",
                "type": [
                    "Text"
                ]
            },
            {
                "name": "character",
                "desc": "Fictional person connected with a creative work.",
                "type": [
                    "Person"
                ]
            },
            {
                "name": "audience",
                "desc": "An intended audience, i.e. a group for whom something was created.",
                "type": [
                    "Audience"
                ]
            },
            {
                "name": "sourceOrganization",
                "desc": "The Organization on whose behalf the creator was working.",
                "type": [
                    "Organization"
                ]
            },
            {
                "name": "isPartOf",
                "desc": "Indicates a CreativeWork that this CreativeWork is (in some sense) part of.",
                "type": [
                    "CreativeWork"
                ]
            },
            {
                "name": "video",
                "desc": "An embedded video object.",
                "type": [
                    "VideoObject"
                ]
            },
            {
                "name": "publisher",
                "desc": "The publisher of the creative work.",
                "type": [
                    "Organization",
                    "Person"
                ]
            },
            {
                "name": "publication",
                "desc": "A publication event associated with the item.",
                "type": [
                    "PublicationEvent"
                ]
            },
            {
                "name": "text",
                "desc": "The textual content of this CreativeWork.",
                "type": [
                    "Text"
                ]
            },
            {
                "name": "expires",
                "desc": "Date the content expires and is no longer useful or available. For example a <a class=\"localLink\" href=\"http://schema.org/VideoObject\">VideoObject</a> or <a class=\"localLink\" href=\"http://schema.org/NewsArticle\">NewsArticle</a> whose availability or relevance is time-limited, or a <a class=\"localLink\" href=\"http://schema.org/ClaimReview\">ClaimReview</a> fact check whose publisher wants to indicate that it may no longer be relevant (or helpful to highlight) after some date.",
                "type": [
                    "Date"
                ]
            },
            {
                "name": "contributor",
                "desc": "A secondary contributor to the CreativeWork or Event.",
                "type": [
                    "Person",
                    "Organization"
                ]
            },
            {
                "name": "reviews",
                "desc": "Review of the item.",
                "type": [
                    "Review"
                ]
            },
            {
                "name": "typicalAgeRange",
                "desc": "The typical expected age range, e.g. '7-9', '11-'.",
                "type": [
                    "Text"
                ]
            },
            {
                "name": "releasedEvent",
                "desc": "The place and time the release was issued, expressed as a PublicationEvent.",
                "type": [
                    "PublicationEvent"
                ]
            },
            {
                "name": "educationalUse",
                "desc": "The purpose of a work in the context of education; for example, 'assignment', 'group work'.",
                "type": [
                    "Text"
                ]
            },
            {
                "name": "contentLocation",
                "desc": "The location depicted or described in the content. For example, the location in a photograph or painting.",
                "type": [
                    "Place"
                ]
            },
            {
                "name": "schemaVersion",
                "desc": "Indicates (by URL or string) a particular version of a schema used in some CreativeWork. For example, a document could declare a schemaVersion using an URL such as http://schema.org/version/2.0/ if precise indication of schema version was required by some application.",
                "type": [
                    "URL",
                    "Text"
                ]
            },
            {
                "name": "accessibilityFeature",
                "desc": "Content features of the resource, such as accessible media, alternatives and supported enhancements for accessibility (<a href=\"http://www.w3.org/wiki/WebSchemas/Accessibility\">WebSchemas wiki lists possible values</a>).",
                "type": [
                    "Text"
                ]
            },
            {
                "name": "aggregateRating",
                "desc": "The overall rating, based on a collection of reviews or ratings, of the item.",
                "type": [
                    "AggregateRating"
                ]
            },
            {
                "name": "alternativeHeadline",
                "desc": "A secondary title of the CreativeWork.",
                "type": [
                    "Text"
                ]
            },
            {
                "name": "locationCreated",
                "desc": "The location where the CreativeWork was created, which may not be the same as the location depicted in the CreativeWork.",
                "type": [
                    "Place"
                ]
            },
            {
                "name": "accessModeSufficient",
                "desc": "A list of single or combined accessModes that are sufficient to understand all the intellectual content of a resource. Expected values include:  auditory, tactile, textual, visual.",
                "type": [
                    "Text"
                ]
            },
            {
                "name": "temporalCoverage",
                "desc": "The temporalCoverage of a CreativeWork indicates the period that the content applies to, i.e. that it describes, either as a DateTime or as a textual string indicating a time period in <a href=\"https://en.wikipedia.org/wiki/ISO_8601#Time_intervals\">ISO 8601 time interval format</a>. In\n      the case of a Dataset it will typically indicate the relevant time period in a precise notation (e.g. for a 2011 census dataset, the year 2011 would be written \"2011/2012\"). Other forms of content e.g. ScholarlyArticle, Book, TVSeries or TVEpisode may indicate their temporalCoverage in broader terms - textually or via well-known URL.\n      Written works such as books may sometimes have precise temporal coverage too, e.g. a work set in 1939 - 1945 can be indicated in ISO 8601 interval format format via \"1939/1945\".",
                "type": [
                    "DateTime",
                    "URL",
                    "Text"
                ]
            },
            {
                "name": "accountablePerson",
                "desc": "Specifies the Person that is legally accountable for the CreativeWork.",
                "type": [
                    "Person"
                ]
            },
            {
                "name": "spatialCoverage",
                "desc": "The spatialCoverage of a CreativeWork indicates the place(s) which are the focus of the content. It is a subproperty of\n      contentLocation intended primarily for more technical and detailed materials. For example with a Dataset, it indicates\n      areas that the dataset describes: a dataset of New York weather would have spatialCoverage which was the place: the state of New York.",
                "type": [
                    "Place"
                ]
            },
            {
                "name": "offers",
                "desc": "An offer to provide this item&#x2014;for example, an offer to sell a product, rent the DVD of a movie, perform a service, or give away tickets to an event.",
                "type": [
                    "Offer"
                ]
            },
            {
                "name": "editor",
                "desc": "Specifies the Person who edited the CreativeWork.",
                "type": [
                    "Person"
                ]
            },
            {
                "name": "discussionUrl",
                "desc": "A link to the page containing the comments of the CreativeWork.",
                "type": [
                    "URL"
                ]
            },
            {
                "name": "award",
                "desc": "An award won by or for this item.",
                "type": [
                    "Text"
                ]
            },
            {
                "name": "copyrightHolder",
                "desc": "The party holding the legal copyright to the CreativeWork.",
                "type": [
                    "Organization",
                    "Person"
                ]
            },
            {
                "name": "accessibilityHazard",
                "desc": "A characteristic of the described resource that is physiologically dangerous to some users. Related to WCAG 2.0 guideline 2.3 (<a href=\"http://www.w3.org/wiki/WebSchemas/Accessibility\">WebSchemas wiki lists possible values</a>).",
                "type": [
                    "Text"
                ]
            },
            {
                "name": "copyrightYear",
                "desc": "The year during which the claimed copyright for the CreativeWork was first asserted.",
                "type": [
                    "Number"
                ]
            },
            {
                "name": "awards",
                "desc": "Awards won by or for this item.",
                "type": [
                    "Text"
                ]
            },
            {
                "name": "recordedAt",
                "desc": "The Event where the CreativeWork was recorded. The CreativeWork may capture all or part of the event.",
                "type": [
                    "Event"
                ]
            },
            {
                "name": "commentCount",
                "desc": "The number of comments this CreativeWork (e.g. Article, Question or Answer) has received. This is most applicable to works published in Web sites with commenting system; additional comments may exist elsewhere.",
                "type": [
                    "Integer"
                ]
            },
            {
                "name": "fileFormat",
                "desc": "Media type, typically MIME format (see <a href=\"http://www.iana.org/assignments/media-types/media-types.xhtml\">IANA site</a>) of the content e.g. application/zip of a SoftwareApplication binary. In cases where a CreativeWork has several media type representations, 'encoding' can be used to indicate each MediaObject alongside particular fileFormat information. Unregistered or niche file formats can be indicated instead via the most appropriate URL, e.g. defining Web page or a Wikipedia entry.",
                "type": [
                    "URL",
                    "Text"
                ]
            },
            {
                "name": "inLanguage",
                "desc": "The language of the content or performance or used in an action. Please use one of the language codes from the <a href=\"http://tools.ietf.org/html/bcp47\">IETF BCP 47 standard</a>. See also <a class=\"localLink\" href=\"http://schema.org/availableLanguage\">availableLanguage</a>.",
                "type": [
                    "Language",
                    "Text"
                ]
            },
            {
                "name": "accessibilityAPI",
                "desc": "Indicates that the resource is compatible with the referenced accessibility API (<a href=\"http://www.w3.org/wiki/WebSchemas/Accessibility\">WebSchemas wiki lists possible values</a>).",
                "type": [
                    "Text"
                ]
            },
            {
                "name": "interactionStatistic",
                "desc": "The number of interactions for the CreativeWork using the WebSite or SoftwareApplication. The most specific child type of InteractionCounter should be used.",
                "type": [
                    "InteractionCounter"
                ]
            },
            {
                "name": "contentRating",
                "desc": "Official rating of a piece of content&#x2014;for example,'MPAA PG-13'.",
                "type": [
                    "Text"
                ]
            },
            {
                "name": "learningResourceType",
                "desc": "The predominant type or kind characterizing the learning resource. For example, 'presentation', 'handout'.",
                "type": [
                    "Text"
                ]
            },
            {
                "name": "accessMode",
                "desc": "The human sensory perceptual system or cognitive faculty through which a person may process or perceive information. Expected values include: auditory, tactile, textual, visual, colorDependent, chartOnVisual, chemOnVisual, diagramOnVisual, mathOnVisual, musicOnVisual, textOnVisual.",
                "type": [
                    "Text"
                ]
            },
            {
                "name": "material",
                "desc": "A material that something is made from, e.g. leather, wool, cotton, paper.",
                "type": [
                    "Text",
                    "URL",
                    "Product"
                ]
            },
            {
                "name": "isFamilyFriendly",
                "desc": "Indicates whether this content is family friendly.",
                "type": [
                    "Boolean"
                ]
            },
            {
                "name": "exampleOfWork",
                "desc": "A creative work that this work is an example/instance/realization/derivation of.",
                "type": [
                    "CreativeWork"
                ]
            },
            {
                "name": "version",
                "desc": "The version of the CreativeWork embodied by a specified resource.",
                "type": [
                    "Text",
                    "Number"
                ]
            },
            {
                "name": "dateModified",
                "desc": "The date on which the CreativeWork was most recently modified or when the item's entry was modified within a DataFeed.",
                "type": [
                    "DateTime",
                    "Date"
                ]
            },
            {
                "name": "mainEntity",
                "desc": "Indicates the primary entity described in some page or other CreativeWork.",
                "type": [
                    "Thing"
                ]
            },
            {
                "name": "genre",
                "desc": "Genre of the creative work, broadcast channel or group.",
                "type": [
                    "URL",
                    "Text"
                ]
            },
            {
                "name": "keywords",
                "desc": "Keywords or tags used to describe this content. Multiple entries in a keywords list are typically delimited by commas.",
                "type": [
                    "Text"
                ]
            },
            {
                "name": "author",
                "desc": "The author of this content or rating. Please note that author is special in that HTML 5 provides a special mechanism for indicating authorship via the rel tag. That is equivalent to this and may be used interchangeably.",
                "type": [
                    "Organization",
                    "Person"
                ]
            },
            {
                "name": "isBasedOnUrl",
                "desc": "A resource that was used in the creation of this resource. This term can be repeated for multiple sources. For example, http://example.com/great-multiplication-intro.html.",
                "type": [
                    "Product",
                    "CreativeWork",
                    "URL"
                ]
            },
            {
                "name": "timeRequired",
                "desc": "Approximate or typical time it takes to work with or through this learning resource for the typical intended target audience, e.g. 'P30M', 'P1H25M'.",
                "type": [
                    "Duration"
                ]
            },
            {
                "name": "translator",
                "desc": "Organization or person who adapts a creative work to different languages, regional differences and technical requirements of a target market, or that translates during some event.",
                "type": [
                    "Organization",
                    "Person"
                ]
            },
            {
                "name": "thumbnailUrl",
                "desc": "A thumbnail image relevant to the Thing.",
                "type": [
                    "URL"
                ]
            },
            {
                "name": "hasPart",
                "desc": "Indicates a CreativeWork that is (in some sense) a part of this CreativeWork.",
                "type": [
                    "CreativeWork"
                ]
            },
            {
                "name": "comment",
                "desc": "Comments, typically from users.",
                "type": [
                    "Comment"
                ]
            },
            {
                "name": "review",
                "desc": "A review of the item.",
                "type": [
                    "Review"
                ]
            },
            {
                "name": "license",
                "desc": "A license document that applies to this content, typically indicated by URL.",
                "type": [
                    "CreativeWork",
                    "URL"
                ]
            },
            {
                "name": "accessibilityControl",
                "desc": "Identifies input methods that are sufficient to fully control the described resource (<a href=\"http://www.w3.org/wiki/WebSchemas/Accessibility\">WebSchemas wiki lists possible values</a>).",
                "type": [
                    "Text"
                ]
            },
            {
                "name": "encodings",
                "desc": "A media object that encodes this CreativeWork.",
                "type": [
                    "MediaObject"
                ]
            },
            {
                "name": "isBasedOn",
                "desc": "A resource that was used in the creation of this resource. This term can be repeated for multiple sources. For example, http://example.com/great-multiplication-intro.html.",
                "type": [
                    "Product",
                    "CreativeWork",
                    "URL"
                ]
            },
            {
                "name": "creator",
                "desc": "The creator/author of this CreativeWork. This is the same as the Author property for CreativeWork.",
                "type": [
                    "Organization",
                    "Person"
                ]
            },
            {
                "name": "publishingPrinciples",
                "desc": "The publishingPrinciples property indicates (typically via <a class=\"localLink\" href=\"http://schema.org/URL\">URL</a>) a document describing the editorial principles of an <a class=\"localLink\" href=\"http://schema.org/Organization\">Organization</a> (or individual e.g. a <a class=\"localLink\" href=\"http://schema.org/Person\">Person</a> writing a blog) that relate to their activities as a publisher, e.g. ethics or diversity policies. When applied to a <a class=\"localLink\" href=\"http://schema.org/CreativeWork\">CreativeWork</a> (e.g. <a class=\"localLink\" href=\"http://schema.org/NewsArticle\">NewsArticle</a>) the principles are those of the party primarily responsible for the creation of the <a class=\"localLink\" href=\"http://schema.org/CreativeWork\">CreativeWork</a>.</p>\n\n<p>While such policies are most typically expressed in natural language, sometimes related information (e.g. indicating a <a class=\"localLink\" href=\"http://schema.org/funder\">funder</a>) can be expressed using schema.org terminology.",
                "type": [
                    "CreativeWork",
                    "URL"
                ]
            },
            {
                "name": "sponsor",
                "desc": "A person or organization that supports a thing through a pledge, promise, or financial contribution. e.g. a sponsor of a Medical Study or a corporate sponsor of an event.",
                "type": [
                    "Person",
                    "Organization"
                ]
            },
            {
                "name": "producer",
                "desc": "The person or organization who produced the work (e.g. music album, movie, tv/radio series etc.).",
                "type": [
                    "Organization",
                    "Person"
                ]
            },
            {
                "name": "mentions",
                "desc": "Indicates that the CreativeWork contains a reference to, but is not necessarily about a concept.",
                "type": [
                    "Thing"
                ]
            },
            {
                "name": "dateCreated",
                "desc": "The date on which the CreativeWork was created or the item was added to a DataFeed.",
                "type": [
                    "Date",
                    "DateTime"
                ]
            },
            {
                "name": "datePublished",
                "desc": "Date of first broadcast/publication.",
                "type": [
                    "Date"
                ]
            },
            {
                "name": "isAccessibleForFree",
                "desc": "A flag to signal that the item, event, or place is accessible for free.",
                "type": [
                    "Boolean"
                ]
            },
            {
                "name": "headline",
                "desc": "Headline of the article.",
                "type": [
                    "Text"
                ]
            },
            {
                "name": "citation",
                "desc": "A citation or reference to another creative work, such as another publication, web page, scholarly article, etc.",
                "type": [
                    "CreativeWork",
                    "Text"
                ]
            }
        ]
    }
}